kapybara/__init__.py
kapybara/kapybara.py
kapybara-0.1.dist-info/LICENSE
kapybara-0.1.dist-info/METADATA
kapybara-0.1.dist-info/WHEEL
kapybara-0.1.dist-info/top_level.txt
kapybara-0.1.dist-info/RECORD
